Metadata-Version: 2.1
Name: tf2-som
Version: 0.0.10
Summary: Tensorflow 2 implementation of the Self Organizing Maps (SOM)
Home-page: https://odier-io.github.io/tf2-som/
Author: Jérôme ODIER, Nora ACHBAK
Author-email: jerome.odier@lpsc.in2p3.fr, nora.achbak@lpsc.in2p3.fr
License: CeCILL-C
Keywords: som,self organizing map,machine learning
Provides-Extra: pandas
Provides-Extra: astropy
Provides-Extra: matplotlib
License-File: LICENSE.md
